{
 "actions": [],
 "allow_rename": 1,
 "creation": "2022-09-13 19:25:08.501582",
 "doctype": "DocType",
 "editable_grid": 1,
 "engine": "InnoDB",
 "field_order": [
  "title",
  "column_break_2",
  "font_family",
  "column_break_4",
  "font_weight",
  "font_family_name"
 ],
 "fields": [
  {
   "fieldname": "title",
   "fieldtype": "Data",
   "in_global_search": 1,
   "in_list_view": 1,
   "in_standard_filter": 1,
   "label": "Title",
   "read_only": 1
  },
  {
   "fieldname": "column_break_2",
   "fieldtype": "Column Break"
  },
  {
   "fieldname": "font_family",
   "fieldtype": "Link",
   "in_list_view": 1,
   "in_standard_filter": 1,
   "label": "Font Family",
   "options": "CSS Font"
  },
  {
   "fieldname": "column_break_4",
   "fieldtype": "Column Break"
  },
  {
   "fieldname": "font_weight",
   "fieldtype": "Select",
   "in_list_view": 1,
   "in_standard_filter": 1,
   "label": "Font Weight",
   "options": "\n100\n200\n300\n400\n500\n600\n700\n800\n900"
  },
  {
   "fetch_from": "font_family.font_family",
   "fieldname": "font_family_name",
   "fieldtype": "Data",
   "hidden": 1,
   "label": "Font Family Name",
   "read_only": 1
  }
 ],
 "index_web_pages_for_search": 1,
 "istable": 1,
 "links": [],
 "modified": "2022-09-16 15:00:30.505484",
 "modified_by": "Administrator",
 "module": "Go1 CMS",
 "name": "Global Fonts",
 "owner": "Administrator",
 "permissions": [],
 "sort_field": "modified",
 "sort_order": "DESC"
}