[{"name": "PS-24-0000010586", "owner": "Administrator", "creation": "2024-09-10 14:30:15.851796", "modified": "2024-09-10 14:52:15.336002", "modified_by": "Administrator", "docstatus": 0, "idx": 1, "section_title": "Footer About DV Bảo Vệ", "route": "/offers-list?token=gAAAAABm3_qvCREZHUDzVMUAF-WMFfjCggk0ht1q_H50yZHsPcTTzjUuKZN_UkuGQd6dH52vU-TbZx9SkA_dfOgC5k1uhKx_Jv-BmPujLLJ6tSfZKTpoGUA=", "class_name": "czpmijws", "is_template": 1, "section_group": "Footer", "is_full_width": 0, "section_type": "Static Section", "view_type": "", "device_type": "Web & Mobile", "is_editable": 0, "is_login_required": 0, "content_type": "", "fetch_product": 0, "section_name": "Footer About DV Bảo Vệ", "image_option": "Same Document", "allow_update_to_style": 0, "no_of_records": 0, "sort_by": "DESC", "dynamic_data": 1, "display_data_randomly": 0, "enable_view_more": 0, "custom_section_data": "[]", "bg_type": "Color", "bg_color": "#ffffff", "web_template": "<div class=\"footer_p_b mb-6\">\n\t\t\t\t\t\t\t<div class=\"footer-contact-sub-container {{m_sec_item.class_name}}\">\n\t\t\t\t\t\t\t\t<div class=\"my-5\">\n\t\t\t\t\t\t\t\t\t<div class=\"mb-5\">\n\t\t\t\t\t\t\t\t\t\t<img class=\"home__logo max-w-full max-h-10\" src=\"{{m_sec_item.logo}}\" />\n\t\t\t\t\t\t\t\t\t</div>\n\t\t\t\t\t\t\t\t\t<div>\n\t\t\t\t\t\t\t\t\t\t{{m_sec_item.content}}\n\t\t\t\t\t\t\t\t\t</div>\n\t\t\t\t\t\t\t\t</div>\n\t\t\t\t\t\t\t\t<div class=\"flex flex-col gap-4\">\n\t\t\t\t\t\t\t\t\t<div class=\"flex gap-2\">\n\t\t\t\t\t\t\t\t\t\t{% for item in m_sec_item.socials %}\n\t\t\t\t\t\t\t\t\t\t<a class=\"w-8 h-8 max-w-10 p-3 rounded-md flex justify-center items-center hover:bg-gray-300\" href=\"{{ item.redirect_url }}\">\n\t\t\t\t\t\t\t\t\t\t\t<img class=\"address__logo h-4 w-4\" style=\"max-height: 20px;width: 20px;max-width: 20px\" src=\"{{ item.icon }}\" />\n\t\t\t\t\t\t\t\t\t\t</a>\n\t\t\t\t\t\t\t\t\t\t{% endfor %}\n\t\t\t\t\t\t\t\t\t</div>\n\t\t\t\t\t\t\t\t</div>\n\t\t\t\t\t\t\t</div>\n\t\t\t\t\t\t</div>", "doctype": "Page Section", "content": [{"name": "dec83a8840", "owner": "Administrator", "creation": "2024-09-10 14:30:15.851796", "modified": "2024-09-10 14:52:15.336002", "modified_by": "Administrator", "docstatus": 0, "idx": 1, "field_label": "Logo", "field_key": "logo", "field_type": "Attach", "content_type": "Data", "allow_update_to_style": 0, "content": "/files/cropped-mbw.cloud_11-192x192.png", "parent": "PS-24-0000010586", "parentfield": "content", "parenttype": "Page Section", "doctype": "Section Content"}, {"name": "dff0c831b9", "owner": "Administrator", "creation": "2024-09-10 14:30:15.851796", "modified": "2024-09-10 14:52:15.336002", "modified_by": "Administrator", "docstatus": 0, "idx": 2, "field_label": "Nội dung", "field_key": "content", "field_type": "Long Text", "content_type": "Data", "allow_update_to_style": 0, "content": "Công ty tự hào là đối tác tin cậy của nhiều doanh nghiệp, tổ chức và cá nhân, góp phần vào việc bảo vệ an ninh, an toàn cho xã hội.", "parent": "PS-24-0000010586", "parentfield": "content", "parenttype": "Page Section", "doctype": "Section Content"}, {"name": "14e605c8f5", "owner": "Administrator", "creation": "2024-09-10 14:30:15.851796", "modified": "2024-09-10 14:52:15.336002", "modified_by": "Administrator", "docstatus": 0, "idx": 3, "field_label": "Mạng xã hội", "field_key": "socials", "field_type": "List", "content_type": "Data", "allow_update_to_style": 0, "content": "[{\"idx\":1,\"icon\":\"/files/fb_dvbv.svg\",\"redirect_url\":\"#\"},{\"idx\":2,\"icon\":\"/files/ytb_dvbv.svg\",\"redirect_url\":\"#\"},{\"idx\":3,\"icon\":\"/files/tw_dvbv.svg\",\"redirect_url\":\"#\"},{\"idx\":4,\"icon\":\"/files/ig_dvbv.svg\",\"redirect_url\":\"#\"},{\"icon\":\"/files/gg_dvbv.svg\",\"redirect_url\":\"#\",\"idx\":5}]", "fields_json": "[{\"field_label\":\"Icon\",\"field_key\":\"icon\",\"field_type\":\"Attach\",\"idx\":1},{\"field_label\":\"Đường dẫn\",\"field_key\":\"redirect_url\",\"field_type\":\"Text\",\"idx\":2}]", "parent": "PS-24-0000010586", "parentfield": "content", "parenttype": "Page Section", "doctype": "Section Content"}], "section_column_css": [], "column_index": 0}, {"name": "PS-24-0000010585", "owner": "Administrator", "creation": "2024-09-10 14:22:50.311131", "modified": "2024-09-10 14:55:14.695706", "modified_by": "Administrator", "docstatus": 0, "idx": 2, "section_title": "Footer Contact DV Bảo Vệ", "route": "/offers-list?token=gAAAAABm3_tib6ie8Amy3mnX-dw0Q-F1BNFYqjEyy69yMD-OWWZuKbX0wiPXqfzi9F8Pv2bndaMgaU4ZYjjBnDp6fgEusiabugvbFSG9CeJjz0Vq5ekjymg=", "class_name": "cgqmvtmp", "is_template": 1, "section_group": "Footer", "is_full_width": 0, "section_type": "Static Section", "view_type": "", "device_type": "Web & Mobile", "is_editable": 0, "is_login_required": 0, "content_type": "", "fetch_product": 0, "section_name": "Footer Contact DV Bảo Vệ", "image_option": "Same Document", "allow_update_to_style": 0, "no_of_records": 0, "sort_by": "DESC", "dynamic_data": 1, "display_data_randomly": 0, "enable_view_more": 0, "custom_section_data": "[]", "bg_type": "Color", "bg_color": "#ffffff", "web_template": "<div class=\"footer_p_b mb-6\">\n\t\t\t\t\t\t\t<div class=\"{{m_sec_item.class_name}}\">\n\t\t\t\t\t\t\t\t<div class=\"footer-contact-sub-container\" style=\"display:flex;flex-direction: column;\">\n\t\t\t\t\t\t\t\t\t<div class=\"flex title-div mb-4\">\n\t\t\t\t\t\t\t\t\t\t<span  class=\"go1-cms-footer-title\">{{m_sec_item.title or \"\"}}</span>\n\t\t\t\t\t\t\t\t\t</div>\n\t\t\t\t\t\t\t\t\t<div class=\"mb-4\">\n\t\t\t\t\t\t\t\t\t\t{% for item in m_sec_item.contacts %}\n\t\t\t\t\t\t\t\t\t\t<div class=\"address-div py-3 flex gap-6\">\n\t\t\t\t\t\t\t\t\t\t\t<img class=\"address__logo\" style=\"max-height: 20px;width: 20px;max-width: 20px\" src=\"{{ item.icon }}\" />\n\t\t\t\t\t\t\t\t\t\t\t<p class=\"address_content m-0\">\n\t\t\t\t\t\t\t\t\t\t\t\t{{item.address}}\n\t\t\t\t\t\t\t\t\t\t\t</p>\n\t\t\t\t\t\t\t\t\t\t</div>\n\t\t\t\t\t\t\t\t\t\t{% endfor %}\n\t\t\t\t\t\t\t\t\t</div>\n\t\t\t\t\t\t\t\t\t<div class=\"flex gap-2\">\n\t\t\t\t\t\t\t\t\t\t{% for item in m_sec_item.socials %}\n\t\t\t\t\t\t\t\t\t\t<a class=\"w-10 h-10 max-w-10 p-3 rounded-full border border-gray-400 flex justify-center items-center\" href=\"{{ item.redirect_url }}\">\n\t\t\t\t\t\t\t\t\t\t\t<img class=\"address__logo h-4 w-4\" style=\"max-height: 20px;width: 20px;max-width: 20px\" src=\"{{ item.icon }}\" />\n\t\t\t\t\t\t\t\t\t\t</a>\n\t\t\t\t\t\t\t\t\t\t{% endfor %}\n\t\t\t\t\t\t\t\t\t</div>\n\t\t\t\t\t\t\t\t</div>\n\t\t\t\t\t\t\t</div>\n\t\t\t\t\t\t</div>", "doctype": "Page Section", "content": [{"name": "bf0bf2bc57", "owner": "Administrator", "creation": "2024-09-10 14:22:50.311131", "modified": "2024-09-10 14:55:14.695706", "modified_by": "Administrator", "docstatus": 0, "idx": 1, "field_label": "Tiêu đề", "field_key": "title", "field_type": "Text", "content_type": "Data", "allow_update_to_style": 0, "content": "Kết nối với chúng tôi", "parent": "PS-24-0000010585", "parentfield": "content", "parenttype": "Page Section", "doctype": "Section Content"}, {"name": "34283dda19", "owner": "Administrator", "creation": "2024-09-10 14:22:50.311131", "modified": "2024-09-10 14:55:14.695706", "modified_by": "Administrator", "docstatus": 0, "idx": 2, "field_label": "Thông tin liên hệ", "field_key": "contacts", "field_type": "List", "content_type": "Data", "allow_update_to_style": 0, "content": "[{\"idx\":1,\"icon\":\"/files/location_dvbv.svg\",\"address\":\"Tầng 6 , Tòa nhà Technosoft,Phố Duy Tân, phường Dịch Vọng Hậu, Quận Cầu Giấy, Hà Nội ,Việt Nam\"},{\"idx\":2,\"icon\":\"/files/email_dvbv.svg\",\"address\":\"support@mbw.vn\"},{\"idx\":3,\"icon\":\"/files/phone_dvbv.svg\",\"address\":\"1900 6750\"}]", "fields_json": "[{\"field_label\":\"Icon\",\"field_key\":\"icon\",\"field_type\":\"Attach\",\"idx\":1},{\"field_label\":\"Địa chỉ\",\"field_key\":\"address\",\"field_type\":\"Text\",\"idx\":2}]", "parent": "PS-24-0000010585", "parentfield": "content", "parenttype": "Page Section", "doctype": "Section Content"}], "section_column_css": [], "column_index": 1}, {"name": "PS-24-0000010582", "owner": "Administrator", "creation": "2024-09-10 13:53:30.066950", "modified": "2024-09-10 13:54:11.676404", "modified_by": "Administrator", "docstatus": 0, "idx": 3, "section_title": "Menu", "route": "menu", "class_name": "qreviwse", "is_template": 1, "section_group": "Footer", "is_full_width": 0, "section_type": "Menu", "view_type": "", "device_type": "Web & Mobile", "is_editable": 0, "is_login_required": 0, "content_type": "", "fetch_product": 0, "section_name": "Menu", "image_option": "Same Document", "allow_update_to_style": 0, "no_of_records": 0, "sort_by": "DESC", "dynamic_data": 0, "display_data_randomly": 0, "image": "/files/footer Menu.png", "enable_view_more": 0, "custom_section_data": "[]", "bg_type": "Color", "bg_color": "#ffffff", "web_template": "<div class=\"footer_p_b mb-6\">\n\t                                \t \t<div class=\"{{m_sec_item.class_name}}\">\n\t\t\t\t\t\t\t\t\t\t\t\t<div class=\"flex mb-2\">\n\t\t\t\t\t\t\t\t\t\t\t\t\t<span  class=\"go1-cms-footer-title uppercase\">{{m_sec_item.title}}</span>\n\t\t\t\t\t\t\t\t\t\t\t\t</div>\n\t                                \t \t\t<div class=\"border_line\"></div>\n\t                                \t \t\t{%for menu_item in m_sec_item.menus%}\n\t\t                                \t \t\t<div  class=\"d__flex\" style=\"align-items: flex-start;\"><a href=\"{{menu_item.redirect_url}}\" class=\"d__flex go1-cms-footer-text m-0 text-base\">\n\t\t                                \t \t\t{%if footer.enable_link_icon%}<i class=\"fa fa-chevron-right\" style=\"margin-right:5px\"></i>{%endif%}\n\t\t                                \t \t\t<span>{{menu_item.menu_label}}</span></a></div>\n\t\t                                \t \t{%endfor%}\n\t                                \t \t</div>\n\t                                \t \t</div>", "menu": "SYS-M-Bảo Vệ Footer", "doctype": "Page Section", "content": [{"name": "1d487d1748", "owner": "Administrator", "creation": "2024-09-10 13:53:30.066950", "modified": "2024-09-10 13:54:11.667892", "modified_by": "Administrator", "docstatus": 0, "idx": 1, "field_label": "Tiêu đề", "field_key": "title", "field_type": "Text", "content_type": "Data", "allow_update_to_style": 1, "content": "Menu", "parent": "PS-24-0000010582", "parentfield": "content", "parenttype": "Page Section", "doctype": "Section Content"}], "section_column_css": [], "column_index": 2}]